undecorated.py
undecorated-0.3.0.dist-info/DESCRIPTION.rst
undecorated-0.3.0.dist-info/METADATA
undecorated-0.3.0.dist-info/RECORD
undecorated-0.3.0.dist-info/WHEEL
undecorated-0.3.0.dist-info/metadata.json
undecorated-0.3.0.dist-info/top_level.txt
