Metadata-Version: 1.1
Name: undecorated
Version: 0.3.0
Summary: Undecorate python functions, methods or classes
Home-page: https://github.com/mapleoin/undecorated
Author: Ionuț Arțăriși
Author-email: ionut@artarisi.eu
License: UNKNOWN
Platform: UNKNOWN
Classifier: Intended Audience :: Developers
Classifier: License :: OSI Approved :: Apache Software License
Classifier: Programming Language :: Python
